django_kakebo/__init__.py
django_kakebo/admin.py
django_kakebo/apps.py
django_kakebo/constants.py
django_kakebo/forms.py
django_kakebo/types.py
django_kakebo/urls.py
django_kakebo/utils.py
django_kakebo/migrations/0001_initial.py
django_kakebo/migrations/0002_delete_utilitiescost_and_more.py
django_kakebo/migrations/__init__.py
django_kakebo/static/basic/assets/css/bootstrap-icons.css
django_kakebo/static/basic/assets/css/c_style.css
django_kakebo/static/basic/assets/css/calendar.css
django_kakebo/static/basic/assets/css/kakebo-style.css
django_kakebo/static/basic/assets/css/templatemo-topic-listing.css
django_kakebo/static/basic/assets/fonts/bootstrap-icons.woff
django_kakebo/static/basic/assets/fonts/bootstrap-icons.woff2
django_kakebo/static/basic/assets/imgs/kakebo-guide.jpg
django_kakebo/static/basic/assets/imgs/sample.png
django_kakebo/static/basic/assets/js/custom.js
django_kakebo/static/basic/assets/js/jquery.min.js
django_kakebo/static/basic/assets/js/jquery.sticky.js
django_kakebo/static/vendor/bootstrap/css/bootstrap.css
django_kakebo/static/vendor/bootstrap/css/bootstrap.css.map
django_kakebo/static/vendor/bootstrap/css/bootstrap.min.css
django_kakebo/static/vendor/bootstrap/css/bootstrap.min.css.map
django_kakebo/static/vendor/bootstrap/js/bootstrap.bundle.js
django_kakebo/static/vendor/bootstrap/js/bootstrap.bundle.js.map
django_kakebo/static/vendor/bootstrap/js/bootstrap.bundle.min.js
django_kakebo/static/vendor/bootstrap/js/bootstrap.bundle.min.js.map
django_kakebo/static/vendor/icomoon/css/style.css
django_kakebo/static/vendor/icomoon/fonts/icomoon.ttf
django_kakebo/templatetags/__init__.py
django_kakebo/templatetags/render_balance.py
django_kakebo/templatetags/render_budget.py
django_kakebo/templatetags/render_kakebo.py
django_kakebo/views/__init__.py
django_kakebo-0.2.3.data/data/django_kakebo/static/bootstrap-icons.css
django_kakebo-0.2.3.data/data/django_kakebo/static/bootstrap-icons.woff
django_kakebo-0.2.3.dist-info/LICENSE
django_kakebo-0.2.3.dist-info/METADATA
django_kakebo-0.2.3.dist-info/WHEEL
django_kakebo-0.2.3.dist-info/top_level.txt
django_kakebo-0.2.3.dist-info/RECORD
