Metadata-Version: 2.2
Name: django_kakebo
Version: 0.2.3
Summary: A simple django app that exploiting the kakebo method ('primitive_user' app is included).
Home-page: https://github.com/shadMod/django-kakebo/
Download-URL: https://github.com/shadMod/django-kakebo/archive/refs/tags/0.2.3.tar.gz
Author: shadmod
Author-email: support@shadmod.it
Project-URL: Documentation, https://docs.shadmod.it/django_kakebo/index
Project-URL: GitHub, https://github.com/shadMod/django-kakebo/
Project-URL: Bug Tracker, https://github.com/shadMod/django-kakebo/issues/
Classifier: Development Status :: 4 - Beta
Classifier: Intended Audience :: Developers
Classifier: License :: OSI Approved :: MIT License
Classifier: Operating System :: OS Independent
Classifier: Programming Language :: Python :: 3
Classifier: Programming Language :: Python :: 3.8
Classifier: Programming Language :: Python :: 3.9
Classifier: Programming Language :: Python :: 3.10
Classifier: Programming Language :: Python :: 3.11
Requires-Python: >=3.8
License-File: LICENSE
Dynamic: author
Dynamic: author-email
Dynamic: classifier
Dynamic: description
Dynamic: description-content-type
Dynamic: download-url
Dynamic: home-page
Dynamic: project-url
Dynamic: requires-python
Dynamic: summary
